pycount/__init__.py
pycount/core.py
pycount/exceptions.py
pycount/patterns.py
pycount-0.6.18.data/scripts/pycount
pycount-0.6.18.dist-info/DESCRIPTION.rst
pycount-0.6.18.dist-info/LICENSE.txt
pycount-0.6.18.dist-info/METADATA
pycount-0.6.18.dist-info/RECORD
pycount-0.6.18.dist-info/WHEEL
pycount-0.6.18.dist-info/metadata.json
pycount-0.6.18.dist-info/pbr.json
pycount-0.6.18.dist-info/top_level.txt
